dynmap_api/__init__.py
dynmap_api/datastructures/__int__.py
dynmap_api/datastructures/configuration.py
dynmap_api/datastructures/coordinate.py
dynmap_api/datastructures/map.py
dynmap_api/datastructures/player.py
dynmap_api/datastructures/world.py
dynmap_api/datastructures/worldupdate.py
dynmap_api/net/__init__.py
dynmap_api/net/configuration.py
dynmap_api/net/worldupdate.py
dynmap_api-0.1.3.dist-info/LICENSE
dynmap_api-0.1.3.dist-info/WHEEL
dynmap_api-0.1.3.dist-info/METADATA
dynmap_api-0.1.3.dist-info/RECORD
