Metadata-Version: 2.1
Name: dynmap-api
Version: 0.1.3
Summary: A unified Python API wrapper for Dynmap
License: GPLv3
Author: Evan Pratten
Author-email: ewpratten@gmail.com
Requires-Python: >=3.6,<4.0
Classifier: License :: Other/Proprietary License
Classifier: Programming Language :: Python :: 3
Classifier: Programming Language :: Python :: 3.6
Classifier: Programming Language :: Python :: 3.7
Classifier: Programming Language :: Python :: 3.8
Classifier: Programming Language :: Python :: 3.9
Requires-Dist: pydantic (>=1.7.2,<2.0.0)
Requires-Dist: requests (>=2.25.0,<3.0.0)
